touchboard/__init__.py
touchboard-0.1.3.dist-info/WHEEL
touchboard-0.1.3.dist-info/METADATA
touchboard-0.1.3.dist-info/RECORD
