Metadata-Version: 2.1
Name: touchboard
Version: 0.1.3
Summary: 
Author: Python Nerd
Author-email: prajwalmisc@gmail.com
Requires-Python: >=3.8
Classifier: Programming Language :: Python :: 3
Classifier: Programming Language :: Python :: 3.10
Classifier: Programming Language :: Python :: 3.8
Classifier: Programming Language :: Python :: 3.9
Requires-Dist: pyautogui (>=0.9.53)
Requires-Dist: python3-xlib (>=0.15)
